{
  "name": "proto_cells_train_330",
  "width": 256,
  "height": 256,
  "data_label_names": [
    "Blue",
    "Green",
    "Red"
  ],
  "labels": [
    {
      "name": "Green",
      "pixels": [
        {
          "y": 112,
          "x_start": 158,
          "x_end": 167
        },
        {
          "y": 113,
          "x_start": 155,
          "x_end": 170
        },
        {
          "y": 114,
          "x_start": 153,
          "x_end": 172
        },
        {
          "y": 115,
          "x_start": 152,
          "x_end": 173
        },
        {
          "y": 116,
          "x_start": 151,
          "x_end": 174
        },
        {
          "y": 117,
          "x_start": 150,
          "x_end": 175
        },
        {
          "y": 118,
          "x_start": 149,
          "x_end": 176
        },
        {
          "y": 119,
          "x_start": 148,
          "x_end": 177
        },
        {
          "y": 120,
          "x_start": 147,
          "x_end": 178
        },
        {
          "y": 121,
          "x_start": 147,
          "x_end": 178
        },
        {
          "y": 122,
          "x_start": 146,
          "x_end": 179
        },
        {
          "y": 123,
          "x_start": 146,
          "x_end": 179
        },
        {
          "y": 124,
          "x_start": 146,
          "x_end": 179
        },
        {
          "y": 125,
          "x_start": 145,
          "x_end": 180
        },
        {
          "y": 126,
          "x_start": 145,
          "x_end": 180
        },
        {
          "y": 127,
          "x_start": 145,
          "x_end": 180
        },
        {
          "y": 128,
          "x_start": 145,
          "x_end": 180
        },
        {
          "y": 129,
          "x_start": 145,
          "x_end": 180
        },
        {
          "y": 130,
          "x_start": 145,
          "x_end": 180
        },
        {
          "y": 131,
          "x_start": 145,
          "x_end": 180
        },
        {
          "y": 132,
          "x_start": 145,
          "x_end": 180
        },
        {
          "y": 133,
          "x_start": 145,
          "x_end": 180
        },
        {
          "y": 134,
          "x_start": 145,
          "x_end": 180
        },
        {
          "y": 135,
          "x_start": 146,
          "x_end": 179
        },
        {
          "y": 136,
          "x_start": 146,
          "x_end": 179
        },
        {
          "y": 137,
          "x_start": 146,
          "x_end": 179
        },
        {
          "y": 138,
          "x_start": 147,
          "x_end": 178
        },
        {
          "y": 139,
          "x_start": 147,
          "x_end": 178
        },
        {
          "y": 140,
          "x_start": 148,
          "x_end": 177
        },
        {
          "y": 141,
          "x_start": 149,
          "x_end": 176
        },
        {
          "y": 142,
          "x_start": 150,
          "x_end": 175
        },
        {
          "y": 143,
          "x_start": 151,
          "x_end": 174
        },
        {
          "y": 144,
          "x_start": 152,
          "x_end": 173
        },
        {
          "y": 145,
          "x_start": 153,
          "x_end": 172
        },
        {
          "y": 146,
          "x_start": 155,
          "x_end": 170
        },
        {
          "y": 147,
          "x_start": 158,
          "x_end": 167
        }
      ]
    },
    {
      "name": "Green",
      "pixels": [
        {
          "y": 232,
          "x_start": 147,
          "x_end": 156
        },
        {
          "y": 233,
          "x_start": 144,
          "x_end": 159
        },
        {
          "y": 234,
          "x_start": 142,
          "x_end": 160
        },
        {
          "y": 235,
          "x_start": 141,
          "x_end": 162
        },
        {
          "y": 236,
          "x_start": 140,
          "x_end": 163
        },
        {
          "y": 237,
          "x_start": 139,
          "x_end": 164
        },
        {
          "y": 238,
          "x_start": 138,
          "x_end": 165
        },
        {
          "y": 239,
          "x_start": 137,
          "x_end": 166
        },
        {
          "y": 240,
          "x_start": 136,
          "x_end": 167
        },
        {
          "y": 241,
          "x_start": 136,
          "x_end": 167
        },
        {
          "y": 242,
          "x_start": 135,
          "x_end": 168
        },
        {
          "y": 243,
          "x_start": 135,
          "x_end": 168
        },
        {
          "y": 244,
          "x_start": 135,
          "x_end": 168
        },
        {
          "y": 245,
          "x_start": 134,
          "x_end": 169
        },
        {
          "y": 246,
          "x_start": 134,
          "x_end": 169
        },
        {
          "y": 247,
          "x_start": 134,
          "x_end": 169
        },
        {
          "y": 248,
          "x_start": 134,
          "x_end": 169
        },
        {
          "y": 249,
          "x_start": 134,
          "x_end": 169
        },
        {
          "y": 250,
          "x_start": 134,
          "x_end": 169
        },
        {
          "y": 251,
          "x_start": 134,
          "x_end": 169
        },
        {
          "y": 252,
          "x_start": 134,
          "x_end": 169
        },
        {
          "y": 253,
          "x_start": 134,
          "x_end": 169
        },
        {
          "y": 254,
          "x_start": 134,
          "x_end": 169
        },
        {
          "y": 255,
          "x_start": 135,
          "x_end": 168
        }
      ]
    },
    {
      "name": "Green",
      "pixels": [
        {
          "y": 148,
          "x_start": 123,
          "x_end": 138
        },
        {
          "y": 149,
          "x_start": 119,
          "x_end": 142
        },
        {
          "y": 150,
          "x_start": 116,
          "x_end": 145
        },
        {
          "y": 151,
          "x_start": 114,
          "x_end": 147
        },
        {
          "y": 152,
          "x_start": 112,
          "x_end": 149
        },
        {
          "y": 153,
          "x_start": 110,
          "x_end": 151
        },
        {
          "y": 154,
          "x_start": 109,
          "x_end": 152
        },
        {
          "y": 155,
          "x_start": 107,
          "x_end": 154
        },
        {
          "y": 156,
          "x_start": 106,
          "x_end": 155
        },
        {
          "y": 157,
          "x_start": 105,
          "x_end": 156
        },
        {
          "y": 158,
          "x_start": 104,
          "x_end": 158
        },
        {
          "y": 159,
          "x_start": 102,
          "x_end": 159
        },
        {
          "y": 160,
          "x_start": 102,
          "x_end": 160
        },
        {
          "y": 161,
          "x_start": 101,
          "x_end": 160
        },
        {
          "y": 162,
          "x_start": 100,
          "x_end": 161
        },
        {
          "y": 163,
          "x_start": 99,
          "x_end": 162
        },
        {
          "y": 164,
          "x_start": 98,
          "x_end": 163
        },
        {
          "y": 165,
          "x_start": 97,
          "x_end": 164
        },
        {
          "y": 166,
          "x_start": 97,
          "x_end": 164
        },
        {
          "y": 167,
          "x_start": 96,
          "x_end": 165
        },
        {
          "y": 168,
          "x_start": 96,
          "x_end": 165
        },
        {
          "y": 169,
          "x_start": 95,
          "x_end": 166
        },
        {
          "y": 170,
          "x_start": 95,
          "x_end": 166
        },
        {
          "y": 171,
          "x_start": 94,
          "x_end": 167
        },
        {
          "y": 172,
          "x_start": 94,
          "x_end": 167
        },
        {
          "y": 173,
          "x_start": 93,
          "x_end": 168
        },
        {
          "y": 174,
          "x_start": 93,
          "x_end": 168
        },
        {
          "y": 175,
          "x_start": 93,
          "x_end": 168
        },
        {
          "y": 176,
          "x_start": 92,
          "x_end": 169
        },
        {
          "y": 177,
          "x_start": 92,
          "x_end": 169
        },
        {
          "y": 178,
          "x_start": 92,
          "x_end": 169
        },
        {
          "y": 179,
          "x_start": 92,
          "x_end": 169
        },
        {
          "y": 180,
          "x_start": 91,
          "x_end": 170
        },
        {
          "y": 181,
          "x_start": 91,
          "x_end": 170
        },
        {
          "y": 182,
          "x_start": 91,
          "x_end": 170
        },
        {
          "y": 183,
          "x_start": 91,
          "x_end": 170
        },
        {
          "y": 184,
          "x_start": 91,
          "x_end": 170
        },
        {
          "y": 185,
          "x_start": 91,
          "x_end": 170
        },
        {
          "y": 186,
          "x_start": 91,
          "x_end": 170
        },
        {
          "y": 187,
          "x_start": 91,
          "x_end": 170
        },
        {
          "y": 188,
          "x_start": 91,
          "x_end": 170
        },
        {
          "y": 189,
          "x_start": 91,
          "x_end": 170
        },
        {
          "y": 190,
          "x_start": 91,
          "x_end": 170
        },
        {
          "y": 191,
          "x_start": 91,
          "x_end": 170
        },
        {
          "y": 192,
          "x_start": 91,
          "x_end": 170
        },
        {
          "y": 193,
          "x_start": 91,
          "x_end": 170
        },
        {
          "y": 194,
          "x_start": 91,
          "x_end": 170
        },
        {
          "y": 195,
          "x_start": 91,
          "x_end": 170
        },
        {
          "y": 196,
          "x_start": 92,
          "x_end": 169
        },
        {
          "y": 197,
          "x_start": 92,
          "x_end": 169
        },
        {
          "y": 198,
          "x_start": 92,
          "x_end": 169
        },
        {
          "y": 199,
          "x_start": 92,
          "x_end": 169
        },
        {
          "y": 200,
          "x_start": 93,
          "x_end": 168
        },
        {
          "y": 201,
          "x_start": 93,
          "x_end": 168
        },
        {
          "y": 202,
          "x_start": 93,
          "x_end": 168
        },
        {
          "y": 203,
          "x_start": 94,
          "x_end": 167
        },
        {
          "y": 204,
          "x_start": 94,
          "x_end": 167
        },
        {
          "y": 205,
          "x_start": 95,
          "x_end": 166
        },
        {
          "y": 206,
          "x_start": 95,
          "x_end": 166
        },
        {
          "y": 207,
          "x_start": 96,
          "x_end": 165
        },
        {
          "y": 208,
          "x_start": 96,
          "x_end": 165
        },
        {
          "y": 209,
          "x_start": 97,
          "x_end": 164
        },
        {
          "y": 210,
          "x_start": 98,
          "x_end": 163
        },
        {
          "y": 211,
          "x_start": 98,
          "x_end": 163
        },
        {
          "y": 212,
          "x_start": 99,
          "x_end": 162
        },
        {
          "y": 213,
          "x_start": 100,
          "x_end": 161
        },
        {
          "y": 214,
          "x_start": 101,
          "x_end": 160
        },
        {
          "y": 215,
          "x_start": 101,
          "x_end": 159
        },
        {
          "y": 216,
          "x_start": 102,
          "x_end": 159
        },
        {
          "y": 217,
          "x_start": 103,
          "x_end": 158
        },
        {
          "y": 218,
          "x_start": 105,
          "x_end": 156
        },
        {
          "y": 219,
          "x_start": 106,
          "x_end": 155
        },
        {
          "y": 220,
          "x_start": 107,
          "x_end": 154
        },
        {
          "y": 221,
          "x_start": 109,
          "x_end": 152
        },
        {
          "y": 222,
          "x_start": 110,
          "x_end": 151
        },
        {
          "y": 223,
          "x_start": 112,
          "x_end": 149
        },
        {
          "y": 224,
          "x_start": 114,
          "x_end": 147
        },
        {
          "y": 225,
          "x_start": 116,
          "x_end": 145
        },
        {
          "y": 226,
          "x_start": 119,
          "x_end": 142
        },
        {
          "y": 227,
          "x_start": 123,
          "x_end": 138
        }
      ]
    },
    {
      "name": "Red",
      "pixels": [
        {
          "y": 220,
          "x_start": 31,
          "x_end": 40
        },
        {
          "y": 221,
          "x_start": 28,
          "x_end": 43
        },
        {
          "y": 222,
          "x_start": 26,
          "x_end": 45
        },
        {
          "y": 223,
          "x_start": 25,
          "x_end": 46
        },
        {
          "y": 224,
          "x_start": 24,
          "x_end": 47
        },
        {
          "y": 225,
          "x_start": 23,
          "x_end": 48
        },
        {
          "y": 226,
          "x_start": 22,
          "x_end": 49
        },
        {
          "y": 227,
          "x_start": 21,
          "x_end": 50
        },
        {
          "y": 228,
          "x_start": 20,
          "x_end": 51
        },
        {
          "y": 229,
          "x_start": 20,
          "x_end": 51
        },
        {
          "y": 230,
          "x_start": 19,
          "x_end": 52
        },
        {
          "y": 231,
          "x_start": 19,
          "x_end": 52
        },
        {
          "y": 232,
          "x_start": 19,
          "x_end": 52
        },
        {
          "y": 233,
          "x_start": 18,
          "x_end": 53
        },
        {
          "y": 234,
          "x_start": 18,
          "x_end": 53
        },
        {
          "y": 235,
          "x_start": 18,
          "x_end": 53
        },
        {
          "y": 236,
          "x_start": 18,
          "x_end": 53
        },
        {
          "y": 237,
          "x_start": 18,
          "x_end": 53
        },
        {
          "y": 238,
          "x_start": 18,
          "x_end": 53
        },
        {
          "y": 239,
          "x_start": 18,
          "x_end": 53
        },
        {
          "y": 240,
          "x_start": 18,
          "x_end": 53
        },
        {
          "y": 241,
          "x_start": 18,
          "x_end": 53
        },
        {
          "y": 242,
          "x_start": 18,
          "x_end": 53
        },
        {
          "y": 243,
          "x_start": 19,
          "x_end": 52
        },
        {
          "y": 244,
          "x_start": 19,
          "x_end": 52
        },
        {
          "y": 245,
          "x_start": 19,
          "x_end": 52
        },
        {
          "y": 246,
          "x_start": 20,
          "x_end": 51
        },
        {
          "y": 247,
          "x_start": 20,
          "x_end": 51
        },
        {
          "y": 248,
          "x_start": 21,
          "x_end": 50
        },
        {
          "y": 249,
          "x_start": 22,
          "x_end": 49
        },
        {
          "y": 250,
          "x_start": 23,
          "x_end": 48
        },
        {
          "y": 251,
          "x_start": 24,
          "x_end": 47
        },
        {
          "y": 252,
          "x_start": 25,
          "x_end": 46
        },
        {
          "y": 253,
          "x_start": 26,
          "x_end": 45
        },
        {
          "y": 254,
          "x_start": 28,
          "x_end": 43
        },
        {
          "y": 255,
          "x_start": 31,
          "x_end": 40
        }
      ]
    },
    {
      "name": "Blue",
      "pixels": [
        {
          "y": 189,
          "x_start": 246,
          "x_end": 255
        },
        {
          "y": 190,
          "x_start": 243,
          "x_end": 255
        },
        {
          "y": 191,
          "x_start": 241,
          "x_end": 255
        },
        {
          "y": 192,
          "x_start": 239,
          "x_end": 255
        },
        {
          "y": 193,
          "x_start": 238,
          "x_end": 255
        },
        {
          "y": 194,
          "x_start": 237,
          "x_end": 255
        },
        {
          "y": 195,
          "x_start": 236,
          "x_end": 255
        },
        {
          "y": 196,
          "x_start": 235,
          "x_end": 255
        },
        {
          "y": 197,
          "x_start": 234,
          "x_end": 255
        },
        {
          "y": 198,
          "x_start": 234,
          "x_end": 255
        },
        {
          "y": 199,
          "x_start": 233,
          "x_end": 255
        },
        {
          "y": 200,
          "x_start": 233,
          "x_end": 255
        },
        {
          "y": 201,
          "x_start": 232,
          "x_end": 255
        },
        {
          "y": 202,
          "x_start": 232,
          "x_end": 255
        },
        {
          "y": 203,
          "x_start": 232,
          "x_end": 255
        },
        {
          "y": 204,
          "x_start": 231,
          "x_end": 255
        },
        {
          "y": 205,
          "x_start": 231,
          "x_end": 255
        },
        {
          "y": 206,
          "x_start": 231,
          "x_end": 255
        },
        {
          "y": 207,
          "x_start": 231,
          "x_end": 255
        },
        {
          "y": 208,
          "x_start": 231,
          "x_end": 255
        },
        {
          "y": 209,
          "x_start": 231,
          "x_end": 255
        },
        {
          "y": 210,
          "x_start": 231,
          "x_end": 255
        },
        {
          "y": 211,
          "x_start": 231,
          "x_end": 255
        },
        {
          "y": 212,
          "x_start": 231,
          "x_end": 255
        },
        {
          "y": 213,
          "x_start": 231,
          "x_end": 255
        },
        {
          "y": 214,
          "x_start": 232,
          "x_end": 255
        },
        {
          "y": 215,
          "x_start": 232,
          "x_end": 255
        },
        {
          "y": 216,
          "x_start": 232,
          "x_end": 255
        },
        {
          "y": 217,
          "x_start": 233,
          "x_end": 255
        },
        {
          "y": 218,
          "x_start": 233,
          "x_end": 255
        },
        {
          "y": 219,
          "x_start": 234,
          "x_end": 255
        },
        {
          "y": 220,
          "x_start": 234,
          "x_end": 255
        },
        {
          "y": 221,
          "x_start": 235,
          "x_end": 255
        },
        {
          "y": 222,
          "x_start": 236,
          "x_end": 255
        },
        {
          "y": 223,
          "x_start": 237,
          "x_end": 255
        },
        {
          "y": 224,
          "x_start": 238,
          "x_end": 255
        },
        {
          "y": 225,
          "x_start": 239,
          "x_end": 255
        },
        {
          "y": 226,
          "x_start": 241,
          "x_end": 255
        },
        {
          "y": 227,
          "x_start": 243,
          "x_end": 255
        },
        {
          "y": 228,
          "x_start": 246,
          "x_end": 255
        }
      ]
    },
    {
      "name": "Blue",
      "pixels": [
        {
          "y": 0,
          "x_start": 0,
          "x_end": 34
        },
        {
          "y": 1,
          "x_start": 0,
          "x_end": 34
        },
        {
          "y": 2,
          "x_start": 0,
          "x_end": 33
        },
        {
          "y": 3,
          "x_start": 0,
          "x_end": 33
        },
        {
          "y": 4,
          "x_start": 0,
          "x_end": 32
        },
        {
          "y": 5,
          "x_start": 0,
          "x_end": 32
        },
        {
          "y": 6,
          "x_start": 0,
          "x_end": 31
        },
        {
          "y": 7,
          "x_start": 0,
          "x_end": 31
        },
        {
          "y": 8,
          "x_start": 0,
          "x_end": 30
        },
        {
          "y": 9,
          "x_start": 0,
          "x_end": 29
        },
        {
          "y": 10,
          "x_start": 1,
          "x_end": 28
        },
        {
          "y": 11,
          "x_start": 2,
          "x_end": 27
        },
        {
          "y": 12,
          "x_start": 3,
          "x_end": 26
        },
        {
          "y": 13,
          "x_start": 5,
          "x_end": 24
        },
        {
          "y": 14,
          "x_start": 7,
          "x_end": 22
        },
        {
          "y": 15,
          "x_start": 10,
          "x_end": 19
        }
      ]
    }
  ]
}