{
  "name": "proto_cells_train_294",
  "width": 256,
  "height": 256,
  "data_label_names": [
    "Blue",
    "Red"
  ],
  "labels": [
    {
      "name": "Red",
      "pixels": [
        {
          "y": 0,
          "x_start": 54,
          "x_end": 109
        },
        {
          "y": 1,
          "x_start": 54,
          "x_end": 109
        },
        {
          "y": 2,
          "x_start": 55,
          "x_end": 108
        },
        {
          "y": 3,
          "x_start": 55,
          "x_end": 108
        },
        {
          "y": 4,
          "x_start": 56,
          "x_end": 107
        },
        {
          "y": 5,
          "x_start": 57,
          "x_end": 106
        },
        {
          "y": 6,
          "x_start": 58,
          "x_end": 105
        },
        {
          "y": 7,
          "x_start": 59,
          "x_end": 104
        },
        {
          "y": 8,
          "x_start": 60,
          "x_end": 103
        },
        {
          "y": 9,
          "x_start": 61,
          "x_end": 102
        },
        {
          "y": 10,
          "x_start": 62,
          "x_end": 101
        },
        {
          "y": 11,
          "x_start": 63,
          "x_end": 100
        },
        {
          "y": 12,
          "x_start": 65,
          "x_end": 98
        },
        {
          "y": 13,
          "x_start": 67,
          "x_end": 96
        },
        {
          "y": 14,
          "x_start": 69,
          "x_end": 94
        },
        {
          "y": 15,
          "x_start": 71,
          "x_end": 92
        },
        {
          "y": 16,
          "x_start": 75,
          "x_end": 88
        }
      ]
    },
    {
      "name": "Blue",
      "pixels": [
        {
          "y": 152,
          "x_start": 211,
          "x_end": 221
        },
        {
          "y": 153,
          "x_start": 208,
          "x_end": 225
        },
        {
          "y": 154,
          "x_start": 206,
          "x_end": 227
        },
        {
          "y": 155,
          "x_start": 204,
          "x_end": 229
        },
        {
          "y": 156,
          "x_start": 203,
          "x_end": 230
        },
        {
          "y": 157,
          "x_start": 202,
          "x_end": 231
        },
        {
          "y": 158,
          "x_start": 201,
          "x_end": 232
        },
        {
          "y": 159,
          "x_start": 200,
          "x_end": 233
        },
        {
          "y": 160,
          "x_start": 199,
          "x_end": 234
        },
        {
          "y": 161,
          "x_start": 198,
          "x_end": 235
        },
        {
          "y": 162,
          "x_start": 198,
          "x_end": 236
        },
        {
          "y": 163,
          "x_start": 197,
          "x_end": 236
        },
        {
          "y": 164,
          "x_start": 196,
          "x_end": 237
        },
        {
          "y": 165,
          "x_start": 196,
          "x_end": 237
        },
        {
          "y": 166,
          "x_start": 195,
          "x_end": 238
        },
        {
          "y": 167,
          "x_start": 195,
          "x_end": 238
        },
        {
          "y": 168,
          "x_start": 195,
          "x_end": 238
        },
        {
          "y": 169,
          "x_start": 194,
          "x_end": 239
        },
        {
          "y": 170,
          "x_start": 194,
          "x_end": 239
        },
        {
          "y": 171,
          "x_start": 194,
          "x_end": 239
        },
        {
          "y": 172,
          "x_start": 194,
          "x_end": 239
        },
        {
          "y": 173,
          "x_start": 194,
          "x_end": 239
        },
        {
          "y": 174,
          "x_start": 194,
          "x_end": 239
        },
        {
          "y": 175,
          "x_start": 194,
          "x_end": 239
        },
        {
          "y": 176,
          "x_start": 194,
          "x_end": 239
        },
        {
          "y": 177,
          "x_start": 194,
          "x_end": 239
        },
        {
          "y": 178,
          "x_start": 194,
          "x_end": 239
        },
        {
          "y": 179,
          "x_start": 194,
          "x_end": 239
        },
        {
          "y": 180,
          "x_start": 194,
          "x_end": 239
        },
        {
          "y": 181,
          "x_start": 195,
          "x_end": 238
        },
        {
          "y": 182,
          "x_start": 195,
          "x_end": 238
        },
        {
          "y": 183,
          "x_start": 195,
          "x_end": 238
        },
        {
          "y": 184,
          "x_start": 196,
          "x_end": 237
        },
        {
          "y": 185,
          "x_start": 196,
          "x_end": 237
        },
        {
          "y": 186,
          "x_start": 197,
          "x_end": 236
        },
        {
          "y": 187,
          "x_start": 198,
          "x_end": 235
        },
        {
          "y": 188,
          "x_start": 198,
          "x_end": 235
        },
        {
          "y": 189,
          "x_start": 199,
          "x_end": 234
        },
        {
          "y": 190,
          "x_start": 200,
          "x_end": 233
        },
        {
          "y": 191,
          "x_start": 201,
          "x_end": 232
        },
        {
          "y": 192,
          "x_start": 202,
          "x_end": 231
        },
        {
          "y": 193,
          "x_start": 203,
          "x_end": 230
        },
        {
          "y": 194,
          "x_start": 204,
          "x_end": 229
        },
        {
          "y": 195,
          "x_start": 206,
          "x_end": 227
        },
        {
          "y": 196,
          "x_start": 208,
          "x_end": 225
        },
        {
          "y": 197,
          "x_start": 211,
          "x_end": 222
        }
      ]
    },
    {
      "name": "Red",
      "pixels": [
        {
          "y": 106,
          "x_start": 29,
          "x_end": 42
        },
        {
          "y": 107,
          "x_start": 25,
          "x_end": 46
        },
        {
          "y": 108,
          "x_start": 22,
          "x_end": 49
        },
        {
          "y": 109,
          "x_start": 20,
          "x_end": 51
        },
        {
          "y": 110,
          "x_start": 18,
          "x_end": 53
        },
        {
          "y": 111,
          "x_start": 17,
          "x_end": 54
        },
        {
          "y": 112,
          "x_start": 15,
          "x_end": 56
        },
        {
          "y": 113,
          "x_start": 14,
          "x_end": 57
        },
        {
          "y": 114,
          "x_start": 13,
          "x_end": 58
        },
        {
          "y": 115,
          "x_start": 12,
          "x_end": 59
        },
        {
          "y": 116,
          "x_start": 11,
          "x_end": 60
        },
        {
          "y": 117,
          "x_start": 10,
          "x_end": 61
        },
        {
          "y": 118,
          "x_start": 9,
          "x_end": 62
        },
        {
          "y": 119,
          "x_start": 8,
          "x_end": 63
        },
        {
          "y": 120,
          "x_start": 7,
          "x_end": 64
        },
        {
          "y": 121,
          "x_start": 7,
          "x_end": 64
        },
        {
          "y": 122,
          "x_start": 6,
          "x_end": 65
        },
        {
          "y": 123,
          "x_start": 5,
          "x_end": 66
        },
        {
          "y": 124,
          "x_start": 5,
          "x_end": 66
        },
        {
          "y": 125,
          "x_start": 4,
          "x_end": 67
        },
        {
          "y": 126,
          "x_start": 4,
          "x_end": 67
        },
        {
          "y": 127,
          "x_start": 3,
          "x_end": 68
        },
        {
          "y": 128,
          "x_start": 3,
          "x_end": 68
        },
        {
          "y": 129,
          "x_start": 3,
          "x_end": 68
        },
        {
          "y": 130,
          "x_start": 2,
          "x_end": 69
        },
        {
          "y": 131,
          "x_start": 2,
          "x_end": 69
        },
        {
          "y": 132,
          "x_start": 2,
          "x_end": 69
        },
        {
          "y": 133,
          "x_start": 2,
          "x_end": 69
        },
        {
          "y": 134,
          "x_start": 1,
          "x_end": 70
        },
        {
          "y": 135,
          "x_start": 1,
          "x_end": 70
        },
        {
          "y": 136,
          "x_start": 1,
          "x_end": 70
        },
        {
          "y": 137,
          "x_start": 1,
          "x_end": 70
        },
        {
          "y": 138,
          "x_start": 1,
          "x_end": 70
        },
        {
          "y": 139,
          "x_start": 1,
          "x_end": 70
        },
        {
          "y": 140,
          "x_start": 1,
          "x_end": 70
        },
        {
          "y": 141,
          "x_start": 1,
          "x_end": 70
        },
        {
          "y": 142,
          "x_start": 1,
          "x_end": 70
        },
        {
          "y": 143,
          "x_start": 1,
          "x_end": 70
        },
        {
          "y": 144,
          "x_start": 1,
          "x_end": 70
        },
        {
          "y": 145,
          "x_start": 1,
          "x_end": 70
        },
        {
          "y": 146,
          "x_start": 1,
          "x_end": 70
        },
        {
          "y": 147,
          "x_start": 1,
          "x_end": 70
        },
        {
          "y": 148,
          "x_start": 2,
          "x_end": 69
        },
        {
          "y": 149,
          "x_start": 2,
          "x_end": 69
        },
        {
          "y": 150,
          "x_start": 2,
          "x_end": 69
        },
        {
          "y": 151,
          "x_start": 2,
          "x_end": 69
        },
        {
          "y": 152,
          "x_start": 3,
          "x_end": 68
        },
        {
          "y": 153,
          "x_start": 3,
          "x_end": 68
        },
        {
          "y": 154,
          "x_start": 3,
          "x_end": 68
        },
        {
          "y": 155,
          "x_start": 4,
          "x_end": 67
        },
        {
          "y": 156,
          "x_start": 4,
          "x_end": 67
        },
        {
          "y": 157,
          "x_start": 5,
          "x_end": 66
        },
        {
          "y": 158,
          "x_start": 5,
          "x_end": 66
        },
        {
          "y": 159,
          "x_start": 6,
          "x_end": 65
        },
        {
          "y": 160,
          "x_start": 7,
          "x_end": 64
        },
        {
          "y": 161,
          "x_start": 7,
          "x_end": 64
        },
        {
          "y": 162,
          "x_start": 8,
          "x_end": 63
        },
        {
          "y": 163,
          "x_start": 9,
          "x_end": 62
        },
        {
          "y": 164,
          "x_start": 10,
          "x_end": 61
        },
        {
          "y": 165,
          "x_start": 11,
          "x_end": 60
        },
        {
          "y": 166,
          "x_start": 12,
          "x_end": 59
        },
        {
          "y": 167,
          "x_start": 13,
          "x_end": 58
        },
        {
          "y": 168,
          "x_start": 14,
          "x_end": 57
        },
        {
          "y": 169,
          "x_start": 15,
          "x_end": 56
        },
        {
          "y": 170,
          "x_start": 17,
          "x_end": 54
        },
        {
          "y": 171,
          "x_start": 18,
          "x_end": 53
        },
        {
          "y": 172,
          "x_start": 20,
          "x_end": 51
        },
        {
          "y": 173,
          "x_start": 22,
          "x_end": 49
        },
        {
          "y": 174,
          "x_start": 25,
          "x_end": 46
        },
        {
          "y": 175,
          "x_start": 29,
          "x_end": 42
        }
      ]
    },
    {
      "name": "Red",
      "pixels": [
        {
          "y": 231,
          "x_start": 0,
          "x_end": 2
        },
        {
          "y": 232,
          "x_start": 0,
          "x_end": 6
        },
        {
          "y": 233,
          "x_start": 0,
          "x_end": 8
        },
        {
          "y": 234,
          "x_start": 0,
          "x_end": 10
        },
        {
          "y": 235,
          "x_start": 0,
          "x_end": 12
        },
        {
          "y": 236,
          "x_start": 0,
          "x_end": 14
        },
        {
          "y": 237,
          "x_start": 0,
          "x_end": 15
        },
        {
          "y": 238,
          "x_start": 0,
          "x_end": 16
        },
        {
          "y": 239,
          "x_start": 0,
          "x_end": 17
        },
        {
          "y": 240,
          "x_start": 0,
          "x_end": 18
        },
        {
          "y": 241,
          "x_start": 0,
          "x_end": 19
        },
        {
          "y": 242,
          "x_start": 0,
          "x_end": 20
        },
        {
          "y": 243,
          "x_start": 0,
          "x_end": 21
        },
        {
          "y": 244,
          "x_start": 0,
          "x_end": 22
        },
        {
          "y": 245,
          "x_start": 0,
          "x_end": 22
        },
        {
          "y": 246,
          "x_start": 0,
          "x_end": 23
        },
        {
          "y": 247,
          "x_start": 0,
          "x_end": 23
        },
        {
          "y": 248,
          "x_start": 0,
          "x_end": 24
        },
        {
          "y": 249,
          "x_start": 0,
          "x_end": 24
        },
        {
          "y": 250,
          "x_start": 0,
          "x_end": 25
        },
        {
          "y": 251,
          "x_start": 0,
          "x_end": 25
        },
        {
          "y": 252,
          "x_start": 0,
          "x_end": 26
        },
        {
          "y": 253,
          "x_start": 0,
          "x_end": 26
        },
        {
          "y": 254,
          "x_start": 0,
          "x_end": 26
        },
        {
          "y": 255,
          "x_start": 0,
          "x_end": 26
        }
      ]
    }
  ]
}